naylence/agent/__init__.py
naylence/agent/a2a_types.py
naylence/agent/agent.py
naylence/agent/agent_api_router.py
naylence/agent/agent_proxy.py
naylence/agent/background_task_agent.py
naylence/agent/base_agent.py
naylence/agent/configs.py
naylence/agent/errors.py
naylence/agent/gateway/__init__.py
naylence/agent/gateway/agent_http_gateway_listener.py
naylence/agent/gateway/agent_http_gateway_listener_factory.py
naylence/agent/public_api.py
naylence/agent/rpc_adapter.py
naylence/agent/util.py
naylence_agent_sdk-0.4.9.dist-info/METADATA
naylence_agent_sdk-0.4.9.dist-info/WHEEL
naylence_agent_sdk-0.4.9.dist-info/entry_points.txt
naylence_agent_sdk-0.4.9.dist-info/licenses/LICENSE
naylence_agent_sdk-0.4.9.dist-info/RECORD
