Metadata-Version: 2.4
Name: naylence-agent-sdk
Version: 0.4.9
Summary: Naylence Agent SDK
License: Apache-2.0
License-File: LICENSE
Keywords: messaging,ai,agents,platform,naylence
Author: naylencedev@gmail.com
Requires-Python: >=3.12
Classifier: Development Status :: 4 - Beta
Classifier: Intended Audience :: Developers
Classifier: License :: OSI Approved :: Apache Software License
Classifier: Programming Language :: Python :: 3
Classifier: Programming Language :: Python :: 3.12
Classifier: Topic :: Software Development :: Libraries :: Python Modules
Classifier: Topic :: System :: Distributed Computing
Requires-Dist: naylence-runtime (>=0.4.11,<0.5.0)
Project-URL: Bug Tracker, https://github.com/naylence/naylence-agent-sdk-python/issues
Project-URL: Documentation, https://github.com/naylence/naylence-agent-sdk-python#readme
Project-URL: Homepage, https://github.com/naylence/naylence-agent-sdk-python
Project-URL: Repository, https://github.com/naylence/naylence-agent-sdk-python
